simple_algebra4412064/__init__.py
simple_algebra4412064-1.0.0.dist-info/LICENSE
simple_algebra4412064-1.0.0.dist-info/METADATA
simple_algebra4412064-1.0.0.dist-info/WHEEL
simple_algebra4412064-1.0.0.dist-info/top_level.txt
simple_algebra4412064-1.0.0.dist-info/RECORD
