Metadata-Version: 2.1
Name: simple-algebra4412064
Version: 1.0.0
Summary: A simple package for performing basic arithmetic
Author: Rahul Jha
Author-email: rahul.jha.stats@gmail.com
License: MIT
License-File: LICENSE
